.coveragerc
.manylinux-install.sh
.manylinux.sh
CHANGES.rst
LICENSE.txt
MANIFEST.in
README.rst
appveyor.yml
bootstrap.py
buildout.cfg
setup.cfg
setup.py
tox.ini
patches/pickle_bytes_code.diff
patches/pickle_bytes_tests.diff
src/pikl/__init__.py
src/pikl/_pickle_27.c
src/pikl/_pickle_33.c
src/pikl/fastpickle.py
src/pikl/pickle.py
src/pikl/pickle_2.py
src/pikl/pickle_3.py
src/pikl/pickletools_2.py
src/pikl/pickletools_3.py
src/pikl/slowpickle.py
src/pikl.egg-info/PKG-INFO
src/pikl.egg-info/SOURCES.txt
src/pikl.egg-info/dependency_links.txt
src/pikl.egg-info/not-zip-safe
src/pikl.egg-info/requires.txt
src/pikl.egg-info/top_level.txt
src/pikl/tests/__init__.py
src/pikl/tests/pickletester_2.py
src/pikl/tests/pickletester_3.py
src/pikl/tests/test_pickle.py
src/pikl/tests/test_pickle_2.py
src/pikl/tests/test_pickle_3.py
src/pikl/tests/test_pickletools.py