Metadata-Version: 2.1
Name: pikl
Version: 0.0.1
Summary: A rehabilitated, less dangerous pickle.
Home-page: https://github.com/moreati/pikl
Author: Alex Willmer
Author-email: alex@moreati.org.uk
License: PSFL 2 and ZPL 2.1
Keywords: pickle
Platform: any
Classifier: Development Status :: 3 - Alpha
Classifier: License :: OSI Approved :: Zope Public License
Classifier: License :: OSI Approved :: Python Software Foundation License
Classifier: Programming Language :: Python
Classifier: Programming Language :: Python :: 2
Classifier: Programming Language :: Python :: 2.7
Classifier: Programming Language :: Python :: 3
Classifier: Programming Language :: Python :: 3.4
Classifier: Programming Language :: Python :: 3.5
Classifier: Programming Language :: Python :: 3.6
Classifier: Programming Language :: Python :: 3.7
Classifier: Programming Language :: Python :: Implementation :: CPython
Classifier: Programming Language :: Python :: Implementation :: PyPy
Classifier: Programming Language :: Python :: Implementation :: Jython
Classifier: Topic :: Database
Classifier: Topic :: Software Development :: Libraries :: Python Modules
Classifier: Operating System :: Microsoft :: Windows
Classifier: Operating System :: Unix
Classifier: Operating System :: MacOS :: MacOS X
Provides-Extra: test
Provides-Extra: testing
